img_classifier/__main__.py
img_classifier/config.py
img_classifier/data/Chess/Bishop/00000000.JPG
img_classifier/data/Chess/Bishop/00000001.jpg
img_classifier/data/Chess/Bishop/00000002.JPG
img_classifier/data/Chess/Bishop/00000003.png
img_classifier/data/Chess/Bishop/00000004.jpg
img_classifier/data/Chess/Bishop/00000006.jpg
img_classifier/data/Chess/Bishop/00000007.jpg
img_classifier/data/Chess/Bishop/00000008.jpg
img_classifier/data/Chess/Bishop/00000009.png
img_classifier/data/Chess/Bishop/00000010.jpg
img_classifier/data/Chess/Bishop/00000011.jpg
img_classifier/data/Chess/Bishop/00000012.jpg
img_classifier/data/Chess/Bishop/00000013.jpg
img_classifier/data/Chess/Bishop/00000015.png
img_classifier/data/Chess/Bishop/00000016.jpg
img_classifier/data/Chess/Bishop/00000017.jpg
img_classifier/data/Chess/Bishop/00000018.jpg
img_classifier/data/Chess/Bishop/00000019.jpg
img_classifier/data/Chess/Bishop/00000020.jpg
img_classifier/data/Chess/Bishop/00000024.jpg
img_classifier/data/Chess/Bishop/00000025.jpg
img_classifier/data/Chess/Bishop/00000026.jpg
img_classifier/data/Chess/Bishop/00000028.jpg
img_classifier/data/Chess/Bishop/00000031.jpg
img_classifier/data/Chess/Bishop/00000034.jpg
img_classifier/data/Chess/Bishop/00000037.jpg
img_classifier/data/Chess/Bishop/00000039.jpg
img_classifier/data/Chess/Bishop/00000042.jpg
img_classifier/data/Chess/Bishop/00000044.png
img_classifier/data/Chess/Bishop/00000049.jpg
img_classifier/data/Chess/Bishop/00000054.jpeg
img_classifier/data/Chess/Bishop/00000061.jpg
img_classifier/data/Chess/Bishop/00000062.jpg
img_classifier/data/Chess/Bishop/00000066.jpg
img_classifier/data/Chess/Bishop/00000068.png
img_classifier/data/Chess/Bishop/00000070.jpg
img_classifier/data/Chess/Bishop/00000071.png
img_classifier/data/Chess/Bishop/00000074.jpg
img_classifier/data/Chess/Bishop/00000075.jpg
img_classifier/data/Chess/Bishop/00000078.jpg
img_classifier/data/Chess/Bishop/00000079.jpg
img_classifier/data/Chess/Bishop/00000081.jpg
img_classifier-0.1.dist-info/WHEEL
img_classifier-0.1.dist-info/METADATA
img_classifier-0.1.dist-info/RECORD
