Metadata-Version: 2.1
Name: img-classifier
Version: 0.1
Summary: 
Author: jy-choi
Author-email: jy.choi@toss.im
Requires-Python: >=3.8,<4.0
Classifier: Programming Language :: Python :: 3
Classifier: Programming Language :: Python :: 3.10
Classifier: Programming Language :: Python :: 3.8
Classifier: Programming Language :: Python :: 3.9
Requires-Dist: pandas (>=1.5.0,<2.0.0)
Requires-Dist: sklearn (>=0.0,<0.1)
Requires-Dist: torch (>=1.12.1,<2.0.0)
Requires-Dist: torchinfo (>=1.7.1,<2.0.0)
Requires-Dist: torchvision (>=0.13.1,<0.14.0)
Requires-Dist: tqdm (>=4.64.1,<5.0.0)
Requires-Dist: transformers (>=4.23.1,<5.0.0)
Requires-Dist: wandb (>=0.13.4,<0.14.0)
